aind_behavior_services/__init__.py
aind_behavior_services/_version.py
aind_behavior_services/base.py
aind_behavior_services/common.py
aind_behavior_services/data_types.py
aind_behavior_services/message_protocol.py
aind_behavior_services/py.typed
aind_behavior_services/rig/__init__.py
aind_behavior_services/rig/_base.py
aind_behavior_services/rig/_harp_gen.py
aind_behavior_services/rig/aind_manipulator.py
aind_behavior_services/rig/cameras.py
aind_behavior_services/rig/harp.py
aind_behavior_services/rig/load_cells.py
aind_behavior_services/rig/olfactometer.py
aind_behavior_services/rig/treadmill.py
aind_behavior_services/rig/utils.py
aind_behavior_services/rig/visual_stimulation.py
aind_behavior_services/rig/water_valve.py
aind_behavior_services/schema/__init__.py
aind_behavior_services/session/__init__.py
aind_behavior_services/task/__init__.py
aind_behavior_services/task/distributions.py
aind_behavior_services/utils.py
aind_behavior_services-0.13.0.dist-info/licenses/LICENSE
aind_behavior_services-0.13.0.dist-info/WHEEL
aind_behavior_services-0.13.0.dist-info/entry_points.txt
aind_behavior_services-0.13.0.dist-info/METADATA
aind_behavior_services-0.13.0.dist-info/RECORD
