Metadata-Version: 2.4
Name: aind-behavior-services
Version: 0.13.0
Summary: A library for defining and maintaining behavior tasks.
Author: Bruno Cruz
Author-email: Bruno Cruz <bruno.cruz@alleninstitute.org>
License-Expression: MIT
License-File: LICENSE
Classifier: Programming Language :: Python :: 3.11
Classifier: Programming Language :: Python :: 3.12
Classifier: Programming Language :: Python :: 3.13
Classifier: Operating System :: Microsoft :: Windows
Requires-Dist: pydantic
Requires-Dist: harp-python
Requires-Dist: aind-behavior-curriculum
Requires-Dist: gitpython
Requires-Dist: semver
Requires-Python: >=3.11
Project-URL: Documentation, https://allenneuraldynamics.github.io/Aind.Behavior.Services/
Project-URL: Repository, https://github.com/AllenNeuralDynamics/Aind.Behavior.Services/
Project-URL: Issues, https://github.com/AllenNeuralDynamics/Aind.Behavior.Services/issues
Project-URL: Changelog, https://github.com/AllenNeuralDynamics/Aind.Behavior.Services/releases
